resources/defaultconfig.yaml
square/__init__.py
square/__main__.py
square/callbacks.py
square/cfgfile.py
square/dtypes.py
square/k8s.py
square/main.py
square/manio.py
square/square.py
square/yaml_io.py
kubernetes_square-2.1.2.dist-info/LICENSE
kubernetes_square-2.1.2.dist-info/METADATA
kubernetes_square-2.1.2.dist-info/WHEEL
kubernetes_square-2.1.2.dist-info/entry_points.txt
kubernetes_square-2.1.2.dist-info/RECORD
