Metadata-Version: 2.1
Name: kubernetes-square
Version: 2.1.2
Summary: 
Author: Oliver Nagy
Author-email: olitheolix@gmail.com
Requires-Python: >=3.10
Classifier: Development Status :: 5 - Production/Stable
Classifier: License :: OSI Approved :: Apache Software License
Classifier: Operating System :: OS Independent
Classifier: Programming Language :: Python :: 3
Classifier: Programming Language :: Python :: 3.10
Classifier: Programming Language :: Python :: 3.11
Classifier: Programming Language :: Python :: 3.12
Classifier: Topic :: Utilities
Requires-Dist: colorama
Requires-Dist: colorlog
Requires-Dist: h2
Requires-Dist: httpx
Requires-Dist: jsonpatch
Requires-Dist: pydantic (>=2.0)
Requires-Dist: pyyaml
Requires-Dist: tenacity
